shio-2.10.1.dist-info/WHEEL
shio-2.10.1.dist-info/top_level.txt
shio-2.10.1.dist-info/RECORD
shio-2.10.1.dist-info/METADATA
shio/__init__.py
shio/debug.so
shio/expr.so
shio/version.so
shio/core.so
shio/lib/bitstream.so
shio/lib/__init__.py
shio/lib/containers.so
shio/lib/hex.so
shio/lib/binary.so
shio/lib/py3compat.so
