Metadata-Version: 2.1
Name: shio
Version: 2.10.1
Summary: A powerful declarative symmetric parser/builder for binary data support cp950
Home-page: http://construct.readthedocs.org
Author: Arkadiusz Bulski, Tomer Filiba, Corbin Simpson, TKHuang
Author-email: arek.bulski@gmail.com, tomerfiliba@gmail.com, MostAwesomeDude@gmail.com, tkhuangs@gmail.com
License: MIT
Keywords: construct,kaitai,declarative,data structure,struct,binary,symmetric,parser,builder,parsing,building,pack,unpack,packer,unpacker
Platform: POSIX
Platform: Windows
Classifier: Development Status :: 5 - Production/Stable
Classifier: License :: OSI Approved :: MIT License
Classifier: Intended Audience :: Developers
Classifier: Topic :: Software Development :: Libraries :: Python Modules
Classifier: Topic :: Software Development :: Build Tools
Classifier: Topic :: Software Development :: Code Generators
Classifier: Programming Language :: Python :: 2
Classifier: Programming Language :: Python :: 2.7
Classifier: Programming Language :: Python :: 3
Classifier: Programming Language :: Python :: 3.3
Classifier: Programming Language :: Python :: 3.4
Classifier: Programming Language :: Python :: 3.5
Classifier: Programming Language :: Python :: 3.6
Classifier: Programming Language :: Python :: 3.7
Classifier: Programming Language :: Python :: Implementation :: CPython
Classifier: Programming Language :: Python :: Implementation :: PyPy
Provides: construct
Provides-Extra: extras
Provides-Extra: extras
Requires-Dist: enum34; extra == 'extras'
Requires-Dist: numpy; extra == 'extras'
Requires-Dist: arrow; extra == 'extras'
Requires-Dist: ruamel.yaml; extra == 'extras'
